{
    "absolutePath": "dataset\\multivul_multiclass_test\\int_over_666.sol",
    "exportedSymbols": {
        "ERC20TokenInterface": [
            8
        ],
        "TwoYearDreamTokensVesting": [
            26
        ]
    },
    "id": 27,
    "nodeType": "SourceUnit",
    "nodes": [
        {
            "baseContracts": [],
            "contractDependencies": [],
            "contractKind": "contract",
            "documentation": null,
            "fullyImplemented": false,
            "id": 8,
            "linearizedBaseContracts": [
                8
            ],
            "name": "ERC20TokenInterface",
            "nodeType": "ContractDefinition",
            "nodes": [
                {
                    "body": null,
                    "documentation": null,
                    "id": 7,
                    "implemented": false,
                    "isConstructor": false,
                    "isDeclaredConst": true,
                    "modifiers": [],
                    "name": "balanceOf",
                    "nodeType": "FunctionDefinition",
                    "parameters": {
                        "id": 3,
                        "nodeType": "ParameterList",
                        "parameters": [
                            {
                                "constant": false,
                                "id": 2,
                                "name": "tokenOwner",
                                "nodeType": "VariableDeclaration",
                                "scope": 7,
                                "src": "56:18:0",
                                "stateVariable": false,
                                "storageLocation": "default",
                                "typeDescriptions": {
                                    "typeIdentifier": "t_address",
                                    "typeString": "address"
                                },
                                "typeName": {
                                    "id": 1,
                                    "name": "address",
                                    "nodeType": "ElementaryTypeName",
                                    "src": "56:7:0",
                                    "typeDescriptions": {
                                        "typeIdentifier": "t_address",
                                        "typeString": "address"
                                    }
                                },
                                "value": null,
                                "visibility": "internal"
                            }
                        ],
                        "src": "55:20:0"
                    },
                    "payable": false,
                    "returnParameters": {
                        "id": 6,
                        "nodeType": "ParameterList",
                        "parameters": [
                            {
                                "constant": false,
                                "id": 5,
                                "name": "balance",
                                "nodeType": "VariableDeclaration",
                                "scope": 7,
                                "src": "103:12:0",
                                "stateVariable": false,
                                "storageLocation": "default",
                                "typeDescriptions": {
                                    "typeIdentifier": "t_uint256",
                                    "typeString": "uint256"
                                },
                                "typeName": {
                                    "id": 4,
                                    "name": "uint",
                                    "nodeType": "ElementaryTypeName",
                                    "src": "103:4:0",
                                    "typeDescriptions": {
                                        "typeIdentifier": "t_uint256",
                                        "typeString": "uint256"
                                    }
                                },
                                "value": null,
                                "visibility": "internal"
                            }
                        ],
                        "src": "102:14:0"
                    },
                    "scope": 8,
                    "src": "36:81:0",
                    "stateMutability": "view",
                    "superFunction": null,
                    "visibility": "external"
                }
            ],
            "scope": 27,
            "src": "1:118:0"
        },
        {
            "baseContracts": [],
            "contractDependencies": [],
            "contractKind": "contract",
            "documentation": null,
            "fullyImplemented": true,
            "id": 26,
            "linearizedBaseContracts": [
                26
            ],
            "name": "TwoYearDreamTokensVesting",
            "nodeType": "ContractDefinition",
            "nodes": [
                {
                    "constant": false,
                    "id": 10,
                    "name": "vestingStartUnixTimestamp",
                    "nodeType": "VariableDeclaration",
                    "scope": 26,
                    "src": "165:40:0",
                    "stateVariable": true,
                    "storageLocation": "default",
                    "typeDescriptions": {
                        "typeIdentifier": "t_uint256",
                        "typeString": "uint256"
                    },
                    "typeName": {
                        "id": 9,
                        "name": "uint256",
                        "nodeType": "ElementaryTypeName",
                        "src": "165:7:0",
                        "typeDescriptions": {
                            "typeIdentifier": "t_uint256",
                            "typeString": "uint256"
                        }
                    },
                    "value": null,
                    "visibility": "public"
                },
                {
                    "body": {
                        "id": 24,
                        "nodeType": "Block",
                        "src": "287:102:0",
                        "statements": [
                            {
                                "expression": {
                                    "argumentTypes": null,
                                    "id": 20,
                                    "isConstant": false,
                                    "isLValue": false,
                                    "isPure": false,
                                    "lValueRequested": false,
                                    "leftHandSide": {
                                        "argumentTypes": null,
                                        "id": 17,
                                        "name": "vestingStartUnixTimestamp",
                                        "nodeType": "Identifier",
                                        "overloadedDeclarations": [],
                                        "referencedDeclaration": 10,
                                        "src": "297:25:0",
                                        "typeDescriptions": {
                                            "typeIdentifier": "t_uint256",
                                            "typeString": "uint256"
                                        }
                                    },
                                    "nodeType": "Assignment",
                                    "operator": "=",
                                    "rightHandSide": {
                                        "argumentTypes": null,
                                        "expression": {
                                            "argumentTypes": null,
                                            "id": 18,
                                            "name": "block",
                                            "nodeType": "Identifier",
                                            "overloadedDeclarations": [],
                                            "referencedDeclaration": 31,
                                            "src": "325:5:0",
                                            "typeDescriptions": {
                                                "typeIdentifier": "t_magic_block",
                                                "typeString": "block"
                                            }
                                        },
                                        "id": 19,
                                        "isConstant": false,
                                        "isLValue": false,
                                        "isPure": false,
                                        "lValueRequested": false,
                                        "memberName": "timestamp",
                                        "nodeType": "MemberAccess",
                                        "referencedDeclaration": null,
                                        "src": "325:15:0",
                                        "typeDescriptions": {
                                            "typeIdentifier": "t_uint256",
                                            "typeString": "uint256"
                                        }
                                    },
                                    "src": "297:43:0",
                                    "typeDescriptions": {
                                        "typeIdentifier": "t_uint256",
                                        "typeString": "uint256"
                                    }
                                },
                                "id": 21,
                                "nodeType": "ExpressionStatement",
                                "src": "297:43:0"
                            },
                            {
                                "expression": {
                                    "argumentTypes": null,
                                    "id": 22,
                                    "name": "vestingStartUnixTimestamp",
                                    "nodeType": "Identifier",
                                    "overloadedDeclarations": [],
                                    "referencedDeclaration": 10,
                                    "src": "357:25:0",
                                    "typeDescriptions": {
                                        "typeIdentifier": "t_uint256",
                                        "typeString": "uint256"
                                    }
                                },
                                "functionReturnParameters": 16,
                                "id": 23,
                                "nodeType": "Return",
                                "src": "350:32:0"
                            }
                        ]
                    },
                    "documentation": null,
                    "id": 25,
                    "implemented": true,
                    "isConstructor": false,
                    "isDeclaredConst": false,
                    "modifiers": [],
                    "name": "initializeVestingFor",
                    "nodeType": "FunctionDefinition",
                    "parameters": {
                        "id": 13,
                        "nodeType": "ParameterList",
                        "parameters": [
                            {
                                "constant": false,
                                "id": 12,
                                "name": "account",
                                "nodeType": "VariableDeclaration",
                                "scope": 25,
                                "src": "243:15:0",
                                "stateVariable": false,
                                "storageLocation": "default",
                                "typeDescriptions": {
                                    "typeIdentifier": "t_address",
                                    "typeString": "address"
                                },
                                "typeName": {
                                    "id": 11,
                                    "name": "address",
                                    "nodeType": "ElementaryTypeName",
                                    "src": "243:7:0",
                                    "typeDescriptions": {
                                        "typeIdentifier": "t_address",
                                        "typeString": "address"
                                    }
                                },
                                "value": null,
                                "visibility": "internal"
                            }
                        ],
                        "src": "242:17:0"
                    },
                    "payable": false,
                    "returnParameters": {
                        "id": 16,
                        "nodeType": "ParameterList",
                        "parameters": [
                            {
                                "constant": false,
                                "id": 15,
                                "name": "",
                                "nodeType": "VariableDeclaration",
                                "scope": 25,
                                "src": "278:7:0",
                                "stateVariable": false,
                                "storageLocation": "default",
                                "typeDescriptions": {
                                    "typeIdentifier": "t_uint256",
                                    "typeString": "uint256"
                                },
                                "typeName": {
                                    "id": 14,
                                    "name": "uint256",
                                    "nodeType": "ElementaryTypeName",
                                    "src": "278:7:0",
                                    "typeDescriptions": {
                                        "typeIdentifier": "t_uint256",
                                        "typeString": "uint256"
                                    }
                                },
                                "value": null,
                                "visibility": "internal"
                            }
                        ],
                        "src": "277:9:0"
                    },
                    "scope": 26,
                    "src": "212:177:0",
                    "stateMutability": "nonpayable",
                    "superFunction": null,
                    "visibility": "external"
                }
            ],
            "scope": 27,
            "src": "123:268:0"
        }
    ],
    "src": "1:390:0"
}