{
    "absolutePath": "dataset\\multivul_multiclass_test\\timest_38421.sol",
    "exportedSymbols": {
        "InternetWall": [
            37
        ]
    },
    "id": 38,
    "nodeType": "SourceUnit",
    "nodes": [
        {
            "baseContracts": [],
            "contractDependencies": [],
            "contractKind": "contract",
            "documentation": null,
            "fullyImplemented": true,
            "id": 37,
            "linearizedBaseContracts": [
                37
            ],
            "name": "InternetWall",
            "nodeType": "ContractDefinition",
            "nodes": [
                {
                    "canonicalName": "InternetWall.Message",
                    "id": 3,
                    "members": [
                        {
                            "constant": false,
                            "id": 2,
                            "name": "timestamp",
                            "nodeType": "VariableDeclaration",
                            "scope": 3,
                            "src": "52:14:0",
                            "stateVariable": false,
                            "storageLocation": "default",
                            "typeDescriptions": {
                                "typeIdentifier": "t_uint256",
                                "typeString": "uint256"
                            },
                            "typeName": {
                                "id": 1,
                                "name": "uint",
                                "nodeType": "ElementaryTypeName",
                                "src": "52:4:0",
                                "typeDescriptions": {
                                    "typeIdentifier": "t_uint256",
                                    "typeString": "uint256"
                                }
                            },
                            "value": null,
                            "visibility": "internal"
                        }
                    ],
                    "name": "Message",
                    "nodeType": "StructDefinition",
                    "scope": 37,
                    "src": "28:45:0",
                    "visibility": "public"
                },
                {
                    "constant": false,
                    "id": 7,
                    "name": "messages",
                    "nodeType": "VariableDeclaration",
                    "scope": 37,
                    "src": "79:20:0",
                    "stateVariable": true,
                    "storageLocation": "default",
                    "typeDescriptions": {
                        "typeIdentifier": "t_array$_t_struct$_Message_$3_storage_$10_storage",
                        "typeString": "struct InternetWall.Message[10]"
                    },
                    "typeName": {
                        "baseType": {
                            "contractScope": null,
                            "id": 4,
                            "name": "Message",
                            "nodeType": "UserDefinedTypeName",
                            "referencedDeclaration": 3,
                            "src": "79:7:0",
                            "typeDescriptions": {
                                "typeIdentifier": "t_struct$_Message_$3_storage_ptr",
                                "typeString": "struct InternetWall.Message"
                            }
                        },
                        "id": 6,
                        "length": {
                            "argumentTypes": null,
                            "hexValue": "3130",
                            "id": 5,
                            "isConstant": false,
                            "isLValue": false,
                            "isPure": false,
                            "kind": "number",
                            "lValueRequested": false,
                            "nodeType": "Literal",
                            "src": "87:2:0",
                            "subdenomination": null,
                            "typeDescriptions": {
                                "typeIdentifier": null,
                                "typeString": null
                            },
                            "value": "10"
                        },
                        "nodeType": "ArrayTypeName",
                        "src": "79:11:0",
                        "typeDescriptions": {
                            "typeIdentifier": "t_array$_t_struct$_Message_$3_storage_$10_storage_ptr",
                            "typeString": "struct InternetWall.Message[10]"
                        }
                    },
                    "value": null,
                    "visibility": "internal"
                },
                {
                    "constant": false,
                    "id": 9,
                    "name": "messagesIndex",
                    "nodeType": "VariableDeclaration",
                    "scope": 37,
                    "src": "105:18:0",
                    "stateVariable": true,
                    "storageLocation": "default",
                    "typeDescriptions": {
                        "typeIdentifier": "t_uint256",
                        "typeString": "uint256"
                    },
                    "typeName": {
                        "id": 8,
                        "name": "uint",
                        "nodeType": "ElementaryTypeName",
                        "src": "105:4:0",
                        "typeDescriptions": {
                            "typeIdentifier": "t_uint256",
                            "typeString": "uint256"
                        }
                    },
                    "value": null,
                    "visibility": "internal"
                },
                {
                    "body": {
                        "id": 35,
                        "nodeType": "Block",
                        "src": "174:179:0",
                        "statements": [
                            {
                                "assignments": [],
                                "declarations": [
                                    {
                                        "constant": false,
                                        "id": 15,
                                        "name": "newMsg",
                                        "nodeType": "VariableDeclaration",
                                        "scope": 36,
                                        "src": "184:21:0",
                                        "stateVariable": false,
                                        "storageLocation": "memory",
                                        "typeDescriptions": {
                                            "typeIdentifier": "t_struct$_Message_$3_memory_ptr",
                                            "typeString": "struct InternetWall.Message"
                                        },
                                        "typeName": {
                                            "contractScope": null,
                                            "id": 14,
                                            "name": "Message",
                                            "nodeType": "UserDefinedTypeName",
                                            "referencedDeclaration": 3,
                                            "src": "184:7:0",
                                            "typeDescriptions": {
                                                "typeIdentifier": "t_struct$_Message_$3_storage_ptr",
                                                "typeString": "struct InternetWall.Message"
                                            }
                                        },
                                        "value": null,
                                        "visibility": "internal"
                                    }
                                ],
                                "id": 16,
                                "initialValue": null,
                                "nodeType": "VariableDeclarationStatement",
                                "src": "184:21:0"
                            },
                            {
                                "expression": {
                                    "argumentTypes": null,
                                    "id": 22,
                                    "isConstant": false,
                                    "isLValue": false,
                                    "isPure": false,
                                    "lValueRequested": false,
                                    "leftHandSide": {
                                        "argumentTypes": null,
                                        "expression": {
                                            "argumentTypes": null,
                                            "id": 17,
                                            "name": "newMsg",
                                            "nodeType": "Identifier",
                                            "overloadedDeclarations": [],
                                            "referencedDeclaration": 15,
                                            "src": "215:6:0",
                                            "typeDescriptions": {
                                                "typeIdentifier": "t_struct$_Message_$3_memory_ptr",
                                                "typeString": "struct InternetWall.Message memory"
                                            }
                                        },
                                        "id": 19,
                                        "isConstant": false,
                                        "isLValue": true,
                                        "isPure": false,
                                        "lValueRequested": true,
                                        "memberName": "timestamp",
                                        "nodeType": "MemberAccess",
                                        "referencedDeclaration": 2,
                                        "src": "215:16:0",
                                        "typeDescriptions": {
                                            "typeIdentifier": "t_uint256",
                                            "typeString": "uint256"
                                        }
                                    },
                                    "nodeType": "Assignment",
                                    "operator": "=",
                                    "rightHandSide": {
                                        "argumentTypes": null,
                                        "expression": {
                                            "argumentTypes": null,
                                            "id": 20,
                                            "name": "block",
                                            "nodeType": "Identifier",
                                            "overloadedDeclarations": [],
                                            "referencedDeclaration": 42,
                                            "src": "234:5:0",
                                            "typeDescriptions": {
                                                "typeIdentifier": "t_magic_block",
                                                "typeString": "block"
                                            }
                                        },
                                        "id": 21,
                                        "isConstant": false,
                                        "isLValue": false,
                                        "isPure": false,
                                        "lValueRequested": false,
                                        "memberName": "timestamp",
                                        "nodeType": "MemberAccess",
                                        "referencedDeclaration": null,
                                        "src": "234:15:0",
                                        "typeDescriptions": {
                                            "typeIdentifier": "t_uint256",
                                            "typeString": "uint256"
                                        }
                                    },
                                    "src": "215:34:0",
                                    "typeDescriptions": {
                                        "typeIdentifier": "t_uint256",
                                        "typeString": "uint256"
                                    }
                                },
                                "id": 23,
                                "nodeType": "ExpressionStatement",
                                "src": "215:34:0"
                            },
                            {
                                "expression": {
                                    "argumentTypes": null,
                                    "id": 28,
                                    "isConstant": false,
                                    "isLValue": false,
                                    "isPure": false,
                                    "lValueRequested": false,
                                    "leftHandSide": {
                                        "argumentTypes": null,
                                        "baseExpression": {
                                            "argumentTypes": null,
                                            "id": 24,
                                            "name": "messages",
                                            "nodeType": "Identifier",
                                            "overloadedDeclarations": [],
                                            "referencedDeclaration": 7,
                                            "src": "259:8:0",
                                            "typeDescriptions": {
                                                "typeIdentifier": "t_array$_t_struct$_Message_$3_storage_$10_storage",
                                                "typeString": "struct InternetWall.Message storage ref[10] storage ref"
                                            }
                                        },
                                        "id": 26,
                                        "indexExpression": {
                                            "argumentTypes": null,
                                            "id": 25,
                                            "name": "messagesIndex",
                                            "nodeType": "Identifier",
                                            "overloadedDeclarations": [],
                                            "referencedDeclaration": 9,
                                            "src": "268:13:0",
                                            "typeDescriptions": {
                                                "typeIdentifier": "t_uint256",
                                                "typeString": "uint256"
                                            }
                                        },
                                        "isConstant": false,
                                        "isLValue": true,
                                        "isPure": false,
                                        "lValueRequested": true,
                                        "nodeType": "IndexAccess",
                                        "src": "259:23:0",
                                        "typeDescriptions": {
                                            "typeIdentifier": "t_struct$_Message_$3_storage",
                                            "typeString": "struct InternetWall.Message storage ref"
                                        }
                                    },
                                    "nodeType": "Assignment",
                                    "operator": "=",
                                    "rightHandSide": {
                                        "argumentTypes": null,
                                        "id": 27,
                                        "name": "newMsg",
                                        "nodeType": "Identifier",
                                        "overloadedDeclarations": [],
                                        "referencedDeclaration": 15,
                                        "src": "285:6:0",
                                        "typeDescriptions": {
                                            "typeIdentifier": "t_struct$_Message_$3_memory_ptr",
                                            "typeString": "struct InternetWall.Message memory"
                                        }
                                    },
                                    "src": "259:32:0",
                                    "typeDescriptions": {
                                        "typeIdentifier": "t_struct$_Message_$3_storage",
                                        "typeString": "struct InternetWall.Message storage ref"
                                    }
                                },
                                "id": 29,
                                "nodeType": "ExpressionStatement",
                                "src": "259:32:0"
                            },
                            {
                                "expression": {
                                    "argumentTypes": null,
                                    "id": 31,
                                    "isConstant": false,
                                    "isLValue": false,
                                    "isPure": false,
                                    "lValueRequested": false,
                                    "nodeType": "UnaryOperation",
                                    "operator": "++",
                                    "prefix": false,
                                    "src": "301:15:0",
                                    "subExpression": {
                                        "argumentTypes": null,
                                        "id": 30,
                                        "name": "messagesIndex",
                                        "nodeType": "Identifier",
                                        "overloadedDeclarations": [],
                                        "referencedDeclaration": 9,
                                        "src": "301:13:0",
                                        "typeDescriptions": {
                                            "typeIdentifier": "t_uint256",
                                            "typeString": "uint256"
                                        }
                                    },
                                    "typeDescriptions": {
                                        "typeIdentifier": "t_uint256",
                                        "typeString": "uint256"
                                    }
                                },
                                "id": 32,
                                "nodeType": "ExpressionStatement",
                                "src": "301:15:0"
                            },
                            {
                                "expression": {
                                    "argumentTypes": null,
                                    "id": 33,
                                    "name": "messagesIndex",
                                    "nodeType": "Identifier",
                                    "overloadedDeclarations": [],
                                    "referencedDeclaration": 9,
                                    "src": "333:13:0",
                                    "typeDescriptions": {
                                        "typeIdentifier": "t_uint256",
                                        "typeString": "uint256"
                                    }
                                },
                                "functionReturnParameters": 13,
                                "id": 34,
                                "nodeType": "Return",
                                "src": "326:20:0"
                            }
                        ]
                    },
                    "documentation": null,
                    "id": 36,
                    "implemented": true,
                    "isConstructor": false,
                    "isDeclaredConst": false,
                    "modifiers": [],
                    "name": "addMessage",
                    "nodeType": "FunctionDefinition",
                    "parameters": {
                        "id": 10,
                        "nodeType": "ParameterList",
                        "parameters": [],
                        "src": "149:2:0"
                    },
                    "payable": true,
                    "returnParameters": {
                        "id": 13,
                        "nodeType": "ParameterList",
                        "parameters": [
                            {
                                "constant": false,
                                "id": 12,
                                "name": "",
                                "nodeType": "VariableDeclaration",
                                "scope": 36,
                                "src": "168:4:0",
                                "stateVariable": false,
                                "storageLocation": "default",
                                "typeDescriptions": {
                                    "typeIdentifier": "t_uint256",
                                    "typeString": "uint256"
                                },
                                "typeName": {
                                    "id": 11,
                                    "name": "uint",
                                    "nodeType": "ElementaryTypeName",
                                    "src": "168:4:0",
                                    "typeDescriptions": {
                                        "typeIdentifier": "t_uint256",
                                        "typeString": "uint256"
                                    }
                                },
                                "value": null,
                                "visibility": "internal"
                            }
                        ],
                        "src": "167:6:0"
                    },
                    "scope": 37,
                    "src": "130:223:0",
                    "stateMutability": "payable",
                    "superFunction": null,
                    "visibility": "public"
                }
            ],
            "scope": 38,
            "src": "0:355:0"
        }
    ],
    "src": "0:355:0"
}